neko/__init__.py
neko/__main__.py
neko/api.py
neko/client.py
neko/errors.py
neko/models.py
neko.py-1.0.1.dist-info/METADATA
neko.py-1.0.1.dist-info/WHEEL
neko.py-1.0.1.dist-info/top_level.txt
neko.py-1.0.1.dist-info/RECORD
